pysamloader/__init__.py
pysamloader/_version.py
pysamloader/chipid.py
pysamloader/cli.py
pysamloader/efcdescriptor.py
pysamloader/log.py
pysamloader/pysamloader.py
pysamloader/samba.py
pysamloader/samdevice.py
pysamloader/terminal.py
pysamloader/devices/AT91SAM7X512.py
pysamloader/devices/ATSAM3U4E.py
pysamloader/devices/__init__.py
pysamloader-0.6.4.dist-info/LICENSE
pysamloader-0.6.4.dist-info/METADATA
pysamloader-0.6.4.dist-info/WHEEL
pysamloader-0.6.4.dist-info/entry_points.txt
pysamloader-0.6.4.dist-info/top_level.txt
pysamloader-0.6.4.dist-info/RECORD
