Metadata-Version: 2.1
Name: pysamloader
Version: 0.6.4
Summary: python library for writing flash on Atmel's ARM chips via SAM-BA.
Home-page: https://github.com/chintal/pysamloader
Author: Chintalagiri Shashank
Author-email: shashank@chintal.in
License: UNKNOWN
Project-URL: Source Repository, https://github.com/chintal/pysamloader/
Project-URL: Documentation, https://pysamloader.readthedocs.io/en/latest/index.html
Project-URL: Issue Tracker, https://github.com/chintal/pysamloader/issues
Keywords: utilities
Platform: any
Classifier: Development Status :: 4 - Beta
Classifier: Topic :: Utilities
Classifier: Topic :: Software Development :: Embedded Systems
Classifier: License :: OSI Approved :: GNU General Public License v3 or later (GPLv3+)
Classifier: Programming Language :: Python
Classifier: Intended Audience :: Developers
Classifier: Natural Language :: English
Classifier: Operating System :: OS Independent
Classifier: Environment :: Console
Classifier: Programming Language :: Python
Classifier: Programming Language :: Python :: 2.7
Classifier: Programming Language :: Python :: 3
Classifier: Programming Language :: Python :: 3.5
Classifier: Programming Language :: Python :: 3.6
Classifier: Programming Language :: Python :: 3.7
Classifier: Programming Language :: Python :: Implementation :: CPython
Classifier: Programming Language :: Python :: Implementation :: PyPy
Requires-Python: >=2.7, !=3.0.*, !=3.1.*, !=3.2.*, !=3.3.*
Requires-Dist: six
Requires-Dist: appdirs
Requires-Dist: xmodem
Requires-Dist: pyserial
Requires-Dist: progress
Requires-Dist: bitstring
Requires-Dist: wheel
Provides-Extra: build
Requires-Dist: setuptools-scm ; extra == 'build'
Requires-Dist: sphinx ; extra == 'build'
Requires-Dist: sphinx-argparse ; extra == 'build'
Requires-Dist: sphinxcontrib-documentedlist ; extra == 'build'
Requires-Dist: alabaster ; extra == 'build'
Requires-Dist: pytest ; extra == 'build'
Requires-Dist: pytest-cov ; extra == 'build'
Requires-Dist: coveralls[yaml] ; extra == 'build'
Requires-Dist: doit ; extra == 'build'
Requires-Dist: pyinstaller ; extra == 'build'
Provides-Extra: dev
Requires-Dist: setuptools-scm ; extra == 'dev'
Requires-Dist: sphinx ; extra == 'dev'
Requires-Dist: sphinx-argparse ; extra == 'dev'
Requires-Dist: sphinxcontrib-documentedlist ; extra == 'dev'
Requires-Dist: alabaster ; extra == 'dev'
Requires-Dist: pytest ; extra == 'dev'
Requires-Dist: pytest-cov ; extra == 'dev'
Requires-Dist: coveralls[yaml] ; extra == 'dev'
Requires-Dist: doit ; extra == 'dev'
Requires-Dist: pyinstaller ; extra == 'dev'
Provides-Extra: docs
Requires-Dist: setuptools-scm ; extra == 'docs'
Requires-Dist: sphinx ; extra == 'docs'
Requires-Dist: sphinx-argparse ; extra == 'docs'
Requires-Dist: sphinxcontrib-documentedlist ; extra == 'docs'
Requires-Dist: alabaster ; extra == 'docs'
Provides-Extra: publish
Requires-Dist: setuptools-scm ; extra == 'publish'
Requires-Dist: sphinx ; extra == 'publish'
Requires-Dist: sphinx-argparse ; extra == 'publish'
Requires-Dist: sphinxcontrib-documentedlist ; extra == 'publish'
Requires-Dist: alabaster ; extra == 'publish'
Requires-Dist: pytest ; extra == 'publish'
Requires-Dist: pytest-cov ; extra == 'publish'
Requires-Dist: coveralls[yaml] ; extra == 'publish'
Requires-Dist: doit ; extra == 'publish'
Requires-Dist: pyinstaller ; extra == 'publish'
Requires-Dist: twine ; extra == 'publish'
Requires-Dist: pygithub ; extra == 'publish'
Provides-Extra: tests
Requires-Dist: setuptools-scm ; extra == 'tests'
Requires-Dist: sphinx ; extra == 'tests'
Requires-Dist: sphinx-argparse ; extra == 'tests'
Requires-Dist: sphinxcontrib-documentedlist ; extra == 'tests'
Requires-Dist: alabaster ; extra == 'tests'
Requires-Dist: pytest ; extra == 'tests'
Requires-Dist: pytest-cov ; extra == 'tests'
Requires-Dist: coveralls[yaml] ; extra == 'tests'
